LICENSE
MANIFEST.in
README.md
SPECIFICATION.md
buildparser.py
setup.cfg
setup.py
buildparser.egg-info/PKG-INFO
buildparser.egg-info/SOURCES.txt
buildparser.egg-info/dependency_links.txt
buildparser.egg-info/requires.txt
buildparser.egg-info/top_level.txt