Metadata-Version: 1.1
Name: buildparser
Version: 0.1.1
Summary: Generic job build specification parser
Home-page: https://github.com/brettlangdon/buildparser
Author: Brett Langdon
Author-email: brett@blangdon.com
License: MIT
Platform: UNKNOWN
Classifier: Intended Audience :: Developers
Classifier: Programming Language :: Python
Classifier: Programming Language :: Python :: 2.6
Classifier: Programming Language :: Python :: 2.7
Classifier: License :: OSI Approved :: MIT License
Classifier: Topic :: Utilities
